<Properties StartupConfiguration="{32E10D39-786C-4E78-BD77-E5B22A4E4ED9}|Default">
  <MonoDevelop.Ide.Workbench ActiveDocument="WebService/Controllers/CommentsController.cs">
    <Files>
      <File FileName="ProjectPortfolio2/DatabaseContext.cs" Line="9" Column="2" />
      <File FileName="ProjectPortfolio2/DatabaseModel/DataService.cs" Line="9" Column="33" />
      <File FileName="WebService/Controllers/CommentsController.cs" Line="23" Column="41" />
    </Files>
  </MonoDevelop.Ide.Workbench>
  <MonoDevelop.Ide.Workspace ActiveConfiguration="Debug" />
  <MonoDevelop.Ide.ItemProperties.WebService PreferredExecutionTarget="MonoDevelop.Default" />
  <MonoDevelop.Ide.DebuggingService.Breakpoints>
    <BreakpointStore />
  </MonoDevelop.Ide.DebuggingService.Breakpoints>
  <MonoDevelop.Ide.DebuggingService.PinnedWatches />
  <MultiItemStartupConfigurations />
  <MonoDevelop.Ide.ItemProperties.ProjectPortfolio2 PreferredExecutionTarget="MonoDevelop.Default" />
</Properties>